{
  "last_updated": "2025-12-26T16:28:34.432889",
  "streams": [
    {
      "channel": "Anushivan10",
      "is_live": true,
      "viewers": "0",
      "game": "Offline",
      "m3u8_url": "https://usher.ttvnw.net/api/channel/hls/Anushivan10.m3u8?sig=8c31935885462c555b0b3d86a15a691fd2b63d04&token={\"adblock\":false,\"authorization\":{\"forbidden\":false,\"reason\":\"\"},\"blackout_enabled\":false,\"channel\":\"anushivan10\",\"channel_id\":1411626302,\"chansub\":{\"restricted_bitrates\":[],\"view_until\":1924905600},\"ci_gb\":false,\"geoblock_reason\":\"\",\"device_id\":null,\"expires\":1766767706,\"extended_history_allowed\":false,\"game\":\"\",\"hide_ads\":false,\"https_required\":true,\"mature\":false,\"partner\":false,\"platform\":\"web\",\"player_type\":\"site\",\"private\":{\"allowed_to_view\":true},\"privileged\":false,\"role\":\"\",\"server_ads\":true,\"show_ads\":true,\"subscriber\":false,\"turbo\":false,\"user_id\":null,\"user_ip\":\"52.165.250.243\",\"version\":3,\"maximum_resolution\":\"FULL_HD\",\"maximum_video_bitrate_kbps\":12500,\"maximum_resolution_reasons\":{\"QUAD_HD\":[\"AUTHZ_NOT_LOGGED_IN\"],\"ULTRA_HD\":[\"AUTHZ_NOT_LOGGED_IN\"]},\"maximum_video_bitrate_kbps_reasons\":[\"AUTHZ_DISALLOWED_BITRATE\"]}",
      "profile_url": "https://twitch.tv/Anushivan10"
    },
    {
      "channel": "arivumani1075",
      "is_live": false,
      "viewers": "0",
      "game": "Offline",
      "m3u8_url": "https://usher.ttvnw.net/api/channel/hls/arivumani1075.m3u8?sig=ef4ddb35f6136d8a1ea835e0fe6898d130ade20f&token={\"adblock\":false,\"authorization\":{\"forbidden\":false,\"reason\":\"\"},\"blackout_enabled\":false,\"channel\":\"arivumani1075\",\"channel_id\":1391583423,\"chansub\":{\"restricted_bitrates\":[],\"view_until\":1924905600},\"ci_gb\":false,\"geoblock_reason\":\"\",\"device_id\":null,\"expires\":1766767707,\"extended_history_allowed\":false,\"game\":\"\",\"hide_ads\":false,\"https_required\":true,\"mature\":false,\"partner\":false,\"platform\":\"web\",\"player_type\":\"site\",\"private\":{\"allowed_to_view\":true},\"privileged\":false,\"role\":\"\",\"server_ads\":true,\"show_ads\":true,\"subscriber\":false,\"turbo\":false,\"user_id\":null,\"user_ip\":\"52.165.250.243\",\"version\":3,\"maximum_resolution\":\"FULL_HD\",\"maximum_video_bitrate_kbps\":12500,\"maximum_resolution_reasons\":{\"QUAD_HD\":[\"AUTHZ_NOT_LOGGED_IN\"],\"ULTRA_HD\":[\"AUTHZ_NOT_LOGGED_IN\"]},\"maximum_video_bitrate_kbps_reasons\":[\"AUTHZ_DISALLOWED_BITRATE\"]}",
      "profile_url": "https://twitch.tv/arivumani1075"
    },
    {
      "channel": "arivumani1076",
      "is_live": false,
      "viewers": "0",
      "game": "Offline",
      "m3u8_url": "https://usher.ttvnw.net/api/channel/hls/arivumani1076.m3u8?sig=690398f58cf96982fe0a0629b6a17d70fbe54fe9&token={\"adblock\":false,\"authorization\":{\"forbidden\":false,\"reason\":\"\"},\"blackout_enabled\":false,\"channel\":\"arivumani1076\",\"channel_id\":1391842368,\"chansub\":{\"restricted_bitrates\":[],\"view_until\":1924905600},\"ci_gb\":false,\"geoblock_reason\":\"\",\"device_id\":null,\"expires\":1766767709,\"extended_history_allowed\":false,\"game\":\"\",\"hide_ads\":false,\"https_required\":true,\"mature\":false,\"partner\":false,\"platform\":\"web\",\"player_type\":\"site\",\"private\":{\"allowed_to_view\":true},\"privileged\":false,\"role\":\"\",\"server_ads\":true,\"show_ads\":true,\"subscriber\":false,\"turbo\":false,\"user_id\":null,\"user_ip\":\"52.165.250.243\",\"version\":3,\"maximum_resolution\":\"FULL_HD\",\"maximum_video_bitrate_kbps\":12500,\"maximum_resolution_reasons\":{\"QUAD_HD\":[\"AUTHZ_NOT_LOGGED_IN\"],\"ULTRA_HD\":[\"AUTHZ_NOT_LOGGED_IN\"]},\"maximum_video_bitrate_kbps_reasons\":[\"AUTHZ_DISALLOWED_BITRATE\"]}",
      "profile_url": "https://twitch.tv/arivumani1076"
    },
    {
      "channel": "arivumani2059",
      "is_live": true,
      "viewers": "0",
      "game": "Offline",
      "m3u8_url": "https://usher.ttvnw.net/api/channel/hls/arivumani2059.m3u8?sig=740b40a9b55dbf05cc29c3b8f2d16ebf246e2497&token={\"adblock\":false,\"authorization\":{\"forbidden\":false,\"reason\":\"\"},\"blackout_enabled\":false,\"channel\":\"arivumani2059\",\"channel_id\":1411986261,\"chansub\":{\"restricted_bitrates\":[],\"view_until\":1924905600},\"ci_gb\":false,\"geoblock_reason\":\"\",\"device_id\":null,\"expires\":1766767710,\"extended_history_allowed\":false,\"game\":\"\",\"hide_ads\":false,\"https_required\":true,\"mature\":false,\"partner\":false,\"platform\":\"web\",\"player_type\":\"site\",\"private\":{\"allowed_to_view\":true},\"privileged\":false,\"role\":\"\",\"server_ads\":true,\"show_ads\":true,\"subscriber\":false,\"turbo\":false,\"user_id\":null,\"user_ip\":\"52.165.250.243\",\"version\":3,\"maximum_resolution\":\"FULL_HD\",\"maximum_video_bitrate_kbps\":12500,\"maximum_resolution_reasons\":{\"QUAD_HD\":[\"AUTHZ_NOT_LOGGED_IN\"],\"ULTRA_HD\":[\"AUTHZ_NOT_LOGGED_IN\"]},\"maximum_video_bitrate_kbps_reasons\":[\"AUTHZ_DISALLOWED_BITRATE\"]}",
      "profile_url": "https://twitch.tv/arivumani2059"
    },
    {
      "channel": "biggbosslive",
      "is_live": false,
      "viewers": "0",
      "game": "Offline",
      "m3u8_url": "https://usher.ttvnw.net/api/channel/hls/biggbosslive.m3u8?sig=8337b36667a8fd5e3d3d7484ee6af572a1019c79&token={\"adblock\":false,\"authorization\":{\"forbidden\":false,\"reason\":\"\"},\"blackout_enabled\":false,\"channel\":\"biggbosslive\",\"channel_id\":165907367,\"chansub\":{\"restricted_bitrates\":[],\"view_until\":1924905600},\"ci_gb\":false,\"geoblock_reason\":\"\",\"device_id\":null,\"expires\":1766767712,\"extended_history_allowed\":false,\"game\":\"\",\"hide_ads\":false,\"https_required\":true,\"mature\":false,\"partner\":false,\"platform\":\"web\",\"player_type\":\"site\",\"private\":{\"allowed_to_view\":true},\"privileged\":false,\"role\":\"\",\"server_ads\":true,\"show_ads\":true,\"subscriber\":false,\"turbo\":false,\"user_id\":null,\"user_ip\":\"52.165.250.243\",\"version\":3,\"maximum_resolution\":\"FULL_HD\",\"maximum_video_bitrate_kbps\":12500,\"maximum_resolution_reasons\":{\"QUAD_HD\":[\"AUTHZ_NOT_LOGGED_IN\"],\"ULTRA_HD\":[\"AUTHZ_NOT_LOGGED_IN\"]},\"maximum_video_bitrate_kbps_reasons\":[\"AUTHZ_DISALLOWED_BITRATE\"]}",
      "profile_url": "https://twitch.tv/biggbosslive"
    },
    {
      "channel": "tamilstream1",
      "is_live": false,
      "viewers": "0",
      "game": "Error",
      "m3u8_url": "",
      "profile_url": "https://twitch.tv/tamilstream1",
      "error": "'NoneType' object is not subscriptable"
    }
  ]
}